httptoolkit/__init__.py
httptoolkit/_version.py
httptoolkit/encoder.py
httptoolkit/errors.py
httptoolkit/header.py
httptoolkit/http_method.py
httptoolkit/request.py
httptoolkit/retry.py
httptoolkit/sent_request.py
httptoolkit/sent_request_log_record.py
httptoolkit/httpx_service/__init__.py
httptoolkit/httpx_service/_async.py
httptoolkit/httpx_service/_sync.py
httptoolkit/response/__init__.py
httptoolkit/response/_base.py
httptoolkit/response/_regular.py
httptoolkit/response/_stream/__init__.py
httptoolkit/response/_stream/_async.py
httptoolkit/response/_stream/_sync.py
httptoolkit/service/__init__.py
httptoolkit/service/_async.py
httptoolkit/service/_sync.py
httptoolkit/transport/__init__.py
httptoolkit/transport/_async_base.py
httptoolkit/transport/_sync_base.py
httptoolkit/transport/_httpx/__init__.py
httptoolkit/transport/_httpx/_async.py
httptoolkit/transport/_httpx/_base.py
httptoolkit/transport/_httpx/_sync.py
httptoolkit/transport/_httpx/_session/__init__.py
httptoolkit/transport/_httpx/_session/_async.py
httptoolkit/transport/_httpx/_session/_sync.py
http_toolkit-1.0.2.dist-info/LICENSE
http_toolkit-1.0.2.dist-info/METADATA
http_toolkit-1.0.2.dist-info/WHEEL
http_toolkit-1.0.2.dist-info/top_level.txt
http_toolkit-1.0.2.dist-info/RECORD
