Metadata-Version: 2.1
Name: http-toolkit
Version: 1.0.2
Summary: Library for creating HTTP clients to various services with flexible transport customization
Author-email: Kontur <python@skbkontur.ru>
Project-URL: homepage, https://github.com/skbkontur/http_toolkit
Classifier: Development Status :: 5 - Production/Stable
Classifier: Environment :: Web Environment
Classifier: Framework :: AsyncIO
Classifier: Framework :: tox
Classifier: Intended Audience :: Information Technology
Classifier: Intended Audience :: Developers
Classifier: Intended Audience :: System Administrators
Classifier: Operating System :: OS Independent
Classifier: License :: OSI Approved :: MIT License
Classifier: Programming Language :: Python :: 3
Classifier: Programming Language :: Python :: 3 :: Only
Classifier: Programming Language :: Python :: 3.9
Classifier: Programming Language :: Python :: 3.10
Classifier: Programming Language :: Python :: 3.11
Classifier: Programming Language :: Python :: 3.12
Classifier: Programming Language :: Python :: 3.13
Classifier: Programming Language :: Python :: Implementation :: CPython
Classifier: Topic :: System :: Networking
Classifier: Topic :: Internet :: WWW/HTTP
Requires-Python: <3.14,>=3.9
License-File: LICENSE
Requires-Dist: httpx~=0.24.1
Provides-Extra: instruments
Requires-Dist: httpx~=0.24.1; extra == "instruments"
Provides-Extra: test
Requires-Dist: pytest==7.0.0; extra == "test"
Requires-Dist: pytest-cov==3.0.0; extra == "test"
Requires-Dist: testfixtures==6.18.3; extra == "test"
Requires-Dist: pytest-asyncio==0.18.3; extra == "test"
Requires-Dist: pytest-httpx==0.22.0; extra == "test"
